pymorphy3/__init__.py
pymorphy3/analyzer.py
pymorphy3/cache.py
pymorphy3/cli.py
pymorphy3/dawg.py
pymorphy3/shapes.py
pymorphy3/tagset.py
pymorphy3/tokenizers.py
pymorphy3/utils.py
pymorphy3/version.py
pymorphy3/lang/__init__.py
pymorphy3/lang/ru/__init__.py
pymorphy3/lang/ru/config.py
pymorphy3/lang/uk/__init__.py
pymorphy3/lang/uk/_prefixes.py
pymorphy3/lang/uk/config.py
pymorphy3/opencorpora_dict/__init__.py
pymorphy3/opencorpora_dict/compile.py
pymorphy3/opencorpora_dict/parse.py
pymorphy3/opencorpora_dict/preprocess.py
pymorphy3/opencorpora_dict/probability.py
pymorphy3/opencorpora_dict/storage.py
pymorphy3/opencorpora_dict/wrapper.py
pymorphy3/units/__init__.py
pymorphy3/units/abbreviations.py
pymorphy3/units/base.py
pymorphy3/units/by_analogy.py
pymorphy3/units/by_hyphen.py
pymorphy3/units/by_lookup.py
pymorphy3/units/by_shape.py
pymorphy3/units/unkn.py
pymorphy3/units/utils.py
mm_pymorphy3-1.1.2.dist-info/AUTHORS.rst
mm_pymorphy3-1.1.2.dist-info/LICENSE.txt
mm_pymorphy3-1.1.2.dist-info/METADATA
mm_pymorphy3-1.1.2.dist-info/WHEEL
mm_pymorphy3-1.1.2.dist-info/entry_points.txt
mm_pymorphy3-1.1.2.dist-info/top_level.txt
mm_pymorphy3-1.1.2.dist-info/RECORD
